{
 "phase96_cluster_hchar": {
  "status": "ok",
  "returncode": 0,
  "duration_s": 4.4,
  "stdout_bytes": 5484,
  "results_files_touched": []
 },
 "astro_crossref": {
  "status": "ok",
  "returncode": 0,
  "duration_s": 0.66,
  "stdout_bytes": 15605,
  "results_files_touched": [
   "astro_crossref_results.json"
  ]
 },
 "astro_label_pipeline": {
  "status": "ok",
  "returncode": 0,
  "duration_s": 0.4,
  "stdout_bytes": 14088,
  "results_files_touched": [
   "astro_label_results.json"
  ]
 },
 "attack_plan": {
  "status": "ok",
  "returncode": 0,
  "duration_s": 1.14,
  "stdout_bytes": 43870,
  "results_files_touched": [
   "attack_plan_results.json"
  ]
 },
 "coptic_probe_expanded": {
  "status": "ok",
  "returncode": 0,
  "duration_s": 77.97,
  "stdout_bytes": 43763,
  "results_files_touched": [
   "coptic_probe_results.json"
  ]
 },
 "crosssign_network": {
  "status": "ok",
  "returncode": 0,
  "duration_s": 0.41,
  "stdout_bytes": 20813,
  "results_files_touched": []
 },
 "currier_ab": {
  "status": "ok",
  "returncode": 0,
  "duration_s": 0.96,
  "stdout_bytes": 12376,
  "results_files_touched": [
   "currier_ab_results.json"
  ]
 },
 "deep_dive": {
  "status": "ok",
  "returncode": 0,
  "duration_s": 1.09,
  "stdout_bytes": 15906,
  "results_files_touched": [
   "deep_dive_results.json"
  ]
 },
 "deep_dive_phase1": {
  "status": "ok",
  "returncode": 0,
  "duration_s": 1.1,
  "stdout_bytes": 17320,
  "results_files_touched": []
 },
 "diacritic_audit": {
  "status": "ok",
  "returncode": 0,
  "duration_s": 0.45,
  "stdout_bytes": 10341,
  "results_files_touched": []
 },
 "download_folios": {
  "status": "skipped",
  "reason": "pure downloader (network, ~1GB)"
 },
 "download_latin": {
  "status": "skipped",
  "reason": "pure downloader (network)"
 },
 "egyptian_connection": {
  "status": "ok",
  "returncode": 0,
  "duration_s": 0.91,
  "stdout_bytes": 26398,
  "results_files_touched": [
   "egyptian_connection_results.json"
  ]
 },
 "f66r_analysis": {
  "status": "ok",
  "returncode": 0,
  "duration_s": 2.01,
  "stdout_bytes": 14279,
  "results_files_touched": [
   "f66r_results.json"
  ]
 },
 "four_tasks_audit": {
  "status": "ok",
  "returncode": 0,
  "duration_s": 18.41,
  "stdout_bytes": 30588,
  "results_files_touched": [
   "four_tasks_audit.json"
  ]
 },
 "freq_rank_mapping": {
  "status": "ok",
  "returncode": 0,
  "duration_s": 1.64,
  "stdout_bytes": 22722,
  "results_files_touched": [
   "freq_rank_results.json"
  ]
 },
 "gallows_semantics": {
  "status": "ok",
  "returncode": 0,
  "duration_s": 1.15,
  "stdout_bytes": 35496,
  "results_files_touched": [
   "gallows_semantics_results.json"
  ]
 },
 "gallows_test": {
  "status": "ok",
  "returncode": 0,
  "duration_s": 21.03,
  "stdout_bytes": 12399,
  "results_files_touched": [
   "gallows_test_results.json"
  ]
 },
 "grammar_extraction": {
  "status": "ok",
  "returncode": 0,
  "duration_s": 0.38,
  "stdout_bytes": 19969,
  "results_files_touched": [
   "grammar_results.json"
  ]
 },
 "hebrew_comparison": {
  "status": "ok",
  "returncode": 0,
  "duration_s": 0.37,
  "stdout_bytes": 13907,
  "results_files_touched": [
   "hebrew_comparison_results.json"
  ]
 },
 "hebrew_deep_analysis": {
  "status": "ok",
  "returncode": 0,
  "duration_s": 41.57,
  "stdout_bytes": 19550,
  "results_files_touched": [
   "hebrew_deep_results.json"
  ]
 },
 "herbal_crossref": {
  "status": "ok",
  "returncode": 0,
  "duration_s": 1.15,
  "stdout_bytes": 17772,
  "results_files_touched": [
   "herbal_crossref_results.json"
  ]
 },
 "herbal_labels": {
  "status": "ok",
  "returncode": 0,
  "duration_s": 0.65,
  "stdout_bytes": 19714,
  "results_files_touched": [
   "herbal_label_results.json"
  ]
 },
 "innermost_ring_dive": {
  "status": "ok",
  "returncode": 0,
  "duration_s": 0.32,
  "stdout_bytes": 26217,
  "results_files_touched": []
 },
 "leo_deepdive": {
  "status": "ok",
  "returncode": 0,
  "duration_s": 0.87,
  "stdout_bytes": 32727,
  "results_files_touched": [
   "leo_deepdive_results.json"
  ]
 },
 "medieval_degrees": {
  "status": "ok",
  "returncode": 0,
  "duration_s": 0.38,
  "stdout_bytes": 15615,
  "results_files_touched": []
 },
 "pharma_comparison": {
  "status": "ok",
  "returncode": 0,
  "duration_s": 1.01,
  "stdout_bytes": 10461,
  "results_files_touched": [
   "pharma_results.json"
  ]
 },
 "phase100_decipherment": {
  "status": "ok",
  "returncode": 0,
  "duration_s": 1801.56,
  "stdout_bytes": 13989,
  "results_files_touched": [
   "phase100_decipherment.json",
   "phase100_decipherment.txt",
   "phase74_paragraph_framing.json",
   "phase74_paragraph_framing.txt"
  ]
 },
 "phase101_currier_ab_dichotomy": {
  "status": "ok",
  "returncode": 0,
  "duration_s": 454.41,
  "stdout_bytes": 14909,
  "results_files_touched": [
   "phase101_currier_ab_dichotomy.json",
   "phase101_currier_ab_dichotomy.txt"
  ]
 },
 "phase102_historical_validation": {
  "status": "ok",
  "returncode": 0,
  "duration_s": 2.51,
  "stdout_bytes": 18242,
  "results_files_touched": [
   "phase102_historical_validation.json",
   "phase102_historical_validation.txt"
  ]
 },
 "phase103_positional_class_decomposition": {
  "status": "ok",
  "returncode": 0,
  "duration_s": 54.58,
  "stdout_bytes": 12571,
  "results_files_touched": [
   "phase103_positional_class_decomposition.json",
   "phase103_positional_class_decomposition.txt"
  ]
 },
 "phase104_latin_ending_test": {
  "status": "ok",
  "returncode": 0,
  "duration_s": 8.42,
  "stdout_bytes": 14402,
  "results_files_touched": [
   "phase104_latin_ending_test.json",
   "phase104_latin_ending_test.txt"
  ]
 },
 "phase105_cappelli_retest": {
  "status": "ok",
  "returncode": 0,
  "duration_s": 53.9,
  "stdout_bytes": 14344,
  "results_files_touched": [
   "phase105_cappelli_retest.json",
   "phase105_cappelli_retest.txt"
  ]
 },
 "phase106_abbreviation_decode": {
  "status": "ok",
  "returncode": 0,
  "duration_s": 0.1,
  "stdout_bytes": 16963,
  "results_files_touched": [
   "phase106_abbreviation_decode.txt"
  ]
 },
 "phase106b_bench_variants": {
  "status": "ok",
  "returncode": 0,
  "duration_s": 0.14,
  "stdout_bytes": 14623,
  "results_files_touched": [
   "phase106b_bench_variants.txt"
  ]
 },
 "phase106c_positional_freq_match": {
  "status": "ok",
  "returncode": 0,
  "duration_s": 6.01,
  "stdout_bytes": 2426,
  "results_files_touched": [
   "phase106c_positional_frequency_match.txt"
  ]
 },
 "phase107_slot_mi_decomposition": {
  "status": "ok",
  "returncode": 0,
  "duration_s": 201.87,
  "stdout_bytes": 9474,
  "results_files_touched": [
   "phase107_slot_mi_decomposition.txt"
  ]
 },
 "phase19_zodiac_alignment": {
  "status": "ok",
  "returncode": 0,
  "duration_s": 1.58,
  "stdout_bytes": 27690,
  "results_files_touched": [
   "phase19_results.json"
  ]
 },
 "phase20_template_subtraction": {
  "status": "ok",
  "returncode": 0,
  "duration_s": 1.21,
  "stdout_bytes": 17462,
  "results_files_touched": [
   "phase20_results.json"
  ]
 },
 "phase21_highest_leverage": {
  "status": "ok",
  "returncode": 0,
  "duration_s": 1.71,
  "stdout_bytes": 18759,
  "results_files_touched": [
   "phase21_results.json"
  ]
 },
 "phase22_unknown_roots": {
  "status": "ok",
  "returncode": 0,
  "duration_s": 1.3,
  "stdout_bytes": 39679,
  "results_files_touched": [
   "phase22_results.json"
  ]
 },
 "phase23_full_translation": {
  "status": "ok",
  "returncode": 0,
  "duration_s": 0.79,
  "stdout_bytes": 48737,
  "results_files_touched": [
   "phase23_results.json"
  ]
 },
 "phase24_classifier_semantics": {
  "status": "ok",
  "returncode": 0,
  "duration_s": 1.82,
  "stdout_bytes": 45170,
  "results_files_touched": [
   "phase24_results.json"
  ]
 },
 "phase25_narrative_translation": {
  "status": "ok",
  "returncode": 0,
  "duration_s": 5.2,
  "stdout_bytes": 75628,
  "results_files_touched": [
   "phase25_results.json"
  ]
 },
 "phase26_expansion": {
  "status": "ok",
  "returncode": 0,
  "duration_s": 3.26,
  "stdout_bytes": 36262,
  "results_files_touched": [
   "phase26_results.json"
  ]
 },
 "phase27_self_audit": {
  "status": "ok",
  "returncode": 0,
  "duration_s": 12.77,
  "stdout_bytes": 26026,
  "results_files_touched": [
   "phase27_output.txt",
   "phase27_results.json"
  ]
 },
 "phase28_statistical": {
  "status": "ok",
  "returncode": 0,
  "duration_s": 30.71,
  "stdout_bytes": 24536,
  "results_files_touched": [
   "phase28_output.txt",
   "phase28_results.json"
  ]
 },
 "phase29_compounds": {
  "status": "ok",
  "returncode": 0,
  "duration_s": 2.52,
  "stdout_bytes": 21859,
  "results_files_touched": [
   "phase29_output.txt",
   "phase29_results.json"
  ]
 },
 "phase30_validation": {
  "status": "ok",
  "returncode": 0,
  "duration_s": 20.46,
  "stdout_bytes": 12170,
  "results_files_touched": [
   "phase30_output.txt",
   "phase30_results.json"
  ]
 },
 "phase31_prefix_paradox": {
  "status": "ok",
  "returncode": 0,
  "duration_s": 2.69,
  "stdout_bytes": 15778,
  "results_files_touched": [
   "phase31_output.txt",
   "phase31_results.json"
  ]
 },
 "phase32_artifact_test": {
  "status": "ok",
  "returncode": 0,
  "duration_s": 2.7,
  "stdout_bytes": 11567,
  "results_files_touched": [
   "phase32_output.txt",
   "phase32_results.json"
  ]
 },
 "phase33_cascade_audit": {
  "status": "ok",
  "returncode": 0,
  "duration_s": 10.56,
  "stdout_bytes": 11483,
  "results_files_touched": [
   "phase33_output.txt",
   "phase33_results.json"
  ]
 },
 "phase34_model_audit": {
  "status": "ok",
  "returncode": 0,
  "duration_s": 3.06,
  "stdout_bytes": 12770,
  "results_files_touched": [
   "phase34_output.txt",
   "phase34_results.json"
  ]
 },
 "phase35_prefix_disentangle": {
  "status": "ok",
  "returncode": 0,
  "duration_s": 1.62,
  "stdout_bytes": 9156,
  "results_files_touched": []
 },
 "phase36_parser_free": {
  "status": "ok",
  "returncode": 0,
  "duration_s": 4.88,
  "stdout_bytes": 9927,
  "results_files_touched": []
 },
 "phase37_parser_free_analysis": {
  "status": "ok",
  "returncode": 0,
  "duration_s": 1.16,
  "stdout_bytes": 14715,
  "results_files_touched": []
 },
 "phase38_bigram_null": {
  "status": "ok",
  "returncode": 0,
  "duration_s": 165.69,
  "stdout_bytes": 7118,
  "results_files_touched": [
   "phase101_currier_ab_dichotomy.json",
   "phase101_currier_ab_dichotomy.txt"
  ]
 }
}